mdformat_taplo/__init__.py
mdformat_taplo/py.typed
mdformat_taplo-0.9.3.dist-info/METADATA
mdformat_taplo-0.9.3.dist-info/WHEEL
mdformat_taplo-0.9.3.dist-info/entry_points.txt
mdformat_taplo-0.9.3.dist-info/licenses/LICENSE
mdformat_taplo-0.9.3.dist-info/RECORD
