Metadata-Version: 2.4
Name: mdformat-taplo
Version: 0.9.3
Summary: Mdformat plugin to format toml code blocks using taplo.
Author-email: Bagard Hoel <hoel.bagard@gmail.com>
License-File: LICENSE
Requires-Python: >=3.8
Requires-Dist: taplo==0.9.3
